customized_decision_tree/__init__.py
customized_decision_tree/decision_tree.py
customized_decision_tree_library-0.1.dist-info/METADATA
customized_decision_tree_library-0.1.dist-info/WHEEL
customized_decision_tree_library-0.1.dist-info/top_level.txt
customized_decision_tree_library-0.1.dist-info/RECORD
